mopidy_mpd/__init__.py
mopidy_mpd/actor.py
mopidy_mpd/dispatcher.py
mopidy_mpd/exceptions.py
mopidy_mpd/ext.conf
mopidy_mpd/formatting.py
mopidy_mpd/network.py
mopidy_mpd/session.py
mopidy_mpd/tokenize.py
mopidy_mpd/translator.py
mopidy_mpd/uri_mapper.py
mopidy_mpd/protocol/__init__.py
mopidy_mpd/protocol/audio_output.py
mopidy_mpd/protocol/channels.py
mopidy_mpd/protocol/command_list.py
mopidy_mpd/protocol/connection.py
mopidy_mpd/protocol/current_playlist.py
mopidy_mpd/protocol/mount.py
mopidy_mpd/protocol/music_db.py
mopidy_mpd/protocol/playback.py
mopidy_mpd/protocol/reflection.py
mopidy_mpd/protocol/status.py
mopidy_mpd/protocol/stickers.py
mopidy_mpd/protocol/stored_playlists.py
mopidy_mpd/protocol/tagtype_list.py
Mopidy_MPD-3.3.0.dist-info/LICENSE
Mopidy_MPD-3.3.0.dist-info/METADATA
Mopidy_MPD-3.3.0.dist-info/WHEEL
Mopidy_MPD-3.3.0.dist-info/entry_points.txt
Mopidy_MPD-3.3.0.dist-info/top_level.txt
Mopidy_MPD-3.3.0.dist-info/RECORD
